frigus/__init__.py
frigus/metadata.py
frigus/multivariate_fit.py
frigus/population.py
frigus/read_collision_coefficients.py
frigus/read_cr_wrathmall.py
frigus/read_einstein_coefficient.py
frigus/read_energy_levels.py
frigus/readers.py
frigus/reduce_to_matrix.py
frigus/species.py
frigus/utils.py
frigus/cooling_function/__init__.py
frigus/cooling_function/fits.py
frigus/cooling_function/grid.py
frigus/readers/__init__.py
frigus/readers/dataset.py
frigus/readers/read_collision_coefficients.py
frigus/readers/read_cr_wrathmall.py
frigus/readers/read_einstein_coefficient.py
frigus/readers/read_energy_levels.py
frigus/solvers/__init__.py
frigus/solvers/analytic.py
frigus/solvers/linear.py
frigus-4.0.1.data/data/data/H2Xvjlevels.cs
frigus-4.0.1.data/data/data/H2Xvjlevels_flower.cs
frigus-4.0.1.data/data/data/H2Xvjlevels_francois_mod.cs
frigus-4.0.1.data/data/data/H2Xvjlevels_lipovka.cs
frigus-4.0.1.data/data/data/H2Xvjlevels_low_energies.dat
frigus-4.0.1.data/data/data/README
frigus-4.0.1.data/data/data/Rates_H_H2.dat
frigus-4.0.1.data/data/data/frequencies_flower
frigus-4.0.1.data/data/data/j2j
frigus-4.0.1.data/data/data/j2jdown
frigus-4.0.1.data/data/data/j2jup
frigus-4.0.1.data/data/data/lev_labels
frigus-4.0.1.data/data/data/lev_labels_flower
frigus-4.0.1.data/data/data/lev_labels_lique
frigus-4.0.1.data/data/data/rad_trans_unique
frigus-4.0.1.data/data/data/temp_gas.txt
frigus-4.0.1.data/data/data/lipovka/H2_CF.f
frigus-4.0.1.data/data/data/lipovka/Rates_H_HD.dat
frigus-4.0.1.data/data/data/lipovka/Rates_H_HD_new.dat
frigus-4.0.1.data/data/data/lipovka/cooling_function_lipovka.dat
frigus-4.0.1.data/data/data/lipovka/cooling_nc=1.0E+07
frigus-4.0.1.data/data/data/lipovka/cooling_nc=1.0E+08
frigus-4.0.1.data/data/data/lipovka/cooling_nc=1.0E+09
frigus-4.0.1.data/data/data/lipovka/cooling_nc=1.0E+10
frigus-4.0.1.data/data/data/lipovka/cooling_nc=1.0E+11
frigus-4.0.1.data/data/data/lipovka/cooling_nc=1.0E+12
frigus-4.0.1.dist-info/DESCRIPTION.rst
frigus-4.0.1.dist-info/METADATA
frigus-4.0.1.dist-info/RECORD
frigus-4.0.1.dist-info/WHEEL
frigus-4.0.1.dist-info/metadata.json
frigus-4.0.1.dist-info/top_level.txt
