Metadata-Version: 2.0
Name: frigus
Version: 4.0.1
Summary: Compute equilibrium and time-dependent popluation level densities
